Metadata-Version: 2.4
Name: llama-index-readers-spotify
Version: 0.4.1
Summary: llama-index readers spotify integration
Author-email: Your Name <you@example.com>
Maintainer: ong
License-Expression: MIT
License-File: LICENSE
Keywords: music,spotify
Requires-Python: <4.0,>=3.9
Requires-Dist: llama-index-core<0.15,>=0.13.0
Requires-Dist: spotipy<3,>=2.23.0
